testable_dependables/__init__.py
testable_dependables/loader.py
testable_dependables/version_retriever.py
testable_dependables-0.1.0.dist-info/licenses/LICENSE
testable_dependables-0.1.0.dist-info/WHEEL
testable_dependables-0.1.0.dist-info/entry_points.txt
testable_dependables-0.1.0.dist-info/METADATA
testable_dependables-0.1.0.dist-info/RECORD
