Metadata-Version: 2.4
Name: testable-dependables
Version: 0.1.0
Summary: Output testable Python versions based on pyproject.toml.
Keywords: python,toml,pyproject
License-Expression: MIT
License-File: LICENSE
Classifier: Programming Language :: Python
Classifier: Programming Language :: Python :: 3.11
Classifier: Programming Language :: Python :: 3.12
Classifier: Programming Language :: Python :: 3.13
Classifier: Programming Language :: Python :: 3.14
Classifier: Programming Language :: Python :: 3.15
Requires-Dist: packaging>=25.0
Requires-Dist: typer>=0.17.4
Requires-Dist: py-eol>=0.2.0
Requires-Python: >=3.11
Project-URL: Homepage, https://github.com/adamghill/testable-dependables/
Project-URL: Repository, https://github.com/adamghill/testable-dependables.git
